slpeters/__init__.py
slpeters/strategy.py
slpeters-0.2.0.dist-info/METADATA
slpeters-0.2.0.dist-info/WHEEL
slpeters-0.2.0.dist-info/entry_points.txt
slpeters-0.2.0.dist-info/RECORD
