Metadata-Version: 2.3
Name: slpeters
Version: 0.2.0
Summary: Add your description here
Requires-Python: >=3.9
Requires-Dist: ipython>=8.18.0
Requires-Dist: zenbt>=0.20.0
